{
	"pattrstorage" : 	{
		"name" : "state",
		"slots" : 		{
			"1" : 			{
				"id" : 1,
				"data" : 				{
					"upshot_polysynth::carrier-attack" : [ 0.0 ],
					"upshot_polysynth::carrier-brightness" : [ 0.0 ],
					"upshot_polysynth::carrier-decay" : [ 0.0 ],
					"upshot_polysynth::carrier-ratio" : [ 0.0 ],
					"upshot_polysynth::carrier-release" : [ 0.0 ],
					"upshot_polysynth::carrier-sustain" : [ 0.0 ],
					"upshot_polysynth::flush" : [ 0.0 ],
					"upshot_polysynth::midiout" : [ 1 ],
					"upshot_polysynth::modulator-attack" : [ 1.437485346916837 ],
					"upshot_polysynth::modulator-decay" : [ 81.965633541668893 ],
					"upshot_polysynth::modulator-release" : [ 81.965633541668623 ],
					"upshot_polysynth::modulator-sustain" : [ 17.32283464566936 ],
					"upshot_polysynth::refresh" : [ 0.0 ],
					"upshot_polysynth::volume" : [ -26.451076834441452 ],
					"upshot_polysynth::wave-type" : [ 1 ],
					"upshot_chords::chords" : [ 55.0 ],
					"upshot_chords::refresh[1]" : [ 0.0 ],
					"upshot_beams::beam" : [ 1.0 ],
					"upshot_beams::live.toggle" : [ 0.0 ],
					"upshot_beams::live.toggle[1]" : [ 1.0 ],
					"upshot_beams::live.toggle[2]" : [ 0.0 ],
					"upshot_beams::live.toggle[3]" : [ 0.0 ],
					"upshot_beams::live.toggle[4]" : [ 0.0 ],
					"upshot_beams::midiout" : [ 2 ],
					"upshot_beams::pitch_01" : [ 61.0 ],
					"upshot_beams::probability-one" : [ 30.0 ],
					"upshot_beams::probability-one[1]" : [ 100.0 ],
					"upshot_beams::probability-one[3]" : [ 0.0 ],
					"upshot_beams::probability-one[4]" : [ 30.0 ],
					"upshot_beams::probability-zero" : [ 100.0 ],
					"upshot_beams::probability-zero[1]" : [ 0.0 ],
					"upshot_beams::probability-zero[2]" : [ 0.0 ],
					"upshot_beams::random-range" : [ 0, 115 ],
					"upshot_beams::random_note_01" : [ 0.0 ],
					"upshot_beams::refresh" : [ 0.0 ],
					"upshot_beams::root" : [ 0.0 ],
					"upshot_beams::scales" : [ 1.0 ],
					"upshot_beams::state" : [ 1.0 ],
					"upshot_beams::velocity_01" : [ 79.999999999999957 ],
					"upshot_output::DSP state" : [ 1.0 ],
					"upshot_output::output volumes" : [ 0.0 ],
					"upshot_mixer::audio to 1" : [ 0.0 ],
					"upshot_mixer::audio to 2" : [ 1.0 ],
					"upshot_mixer::audio to 3" : [ 2.0 ],
					"upshot_mixer::audio to 4" : [ 3.0 ],
					"upshot_mixer::audio to 5" : [ 4.0 ],
					"upshot_mixer::audio to 6" : [ 5.0 ],
					"upshot_mixer::audio to 7" : [ 6.0 ],
					"upshot_mixer::audio to 8" : [ 7.0 ],
					"upshot_mixer::channel 1" : [ 0.0 ],
					"upshot_mixer::channel 2" : [ 0.0 ],
					"upshot_mixer::channel 3" : [ 0.0 ],
					"upshot_mixer::channel 4" : [ 0.0 ],
					"upshot_mixer::channel 5" : [ 0.0 ],
					"upshot_mixer::channel 6" : [ 0.0 ],
					"upshot_mixer::channel 7" : [ 0.0 ],
					"upshot_mixer::channel 8" : [ 0.0 ],
					"upshot_mixer::channel_01_mute" : [ 1.0 ],
					"upshot_mixer::channel_01_solo" : [ 0.0 ],
					"upshot_mixer::channel_01_solo[1]" : [ 0.0 ],
					"upshot_mixer::channel_02_mute" : [ 1.0 ],
					"upshot_mixer::channel_02_solo" : [ 0.0 ],
					"upshot_mixer::channel_02_solo[1]" : [ 0.0 ],
					"upshot_mixer::channel_02_solo[2]" : [ 0.0 ],
					"upshot_mixer::channel_03_mute" : [ 1.0 ],
					"upshot_mixer::channel_03_solo" : [ 0.0 ],
					"upshot_mixer::channel_03_solo[1]" : [ 0.0 ],
					"upshot_mixer::channel_03_solo[2]" : [ 0.0 ],
					"upshot_mixer::channel_04_mute" : [ 1.0 ],
					"upshot_mixer::channel_05_mute" : [ 1.0 ],
					"upshot_mixer::channel_06_mute" : [ 1.0 ],
					"upshot_mixer::channel_07_mute" : [ 1.0 ],
					"upshot_mixer::channel_08_mute" : [ 1.0 ],
					"upshot_transport::bars" : [ 91 ],
					"upshot_transport::beats" : [ 3 ],
					"upshot_transport::bpm" : [ 120.0 ],
					"upshot_transport::click-state" : [ 0.0 ],
					"upshot_transport::live.text" : [ 0.0 ],
					"upshot_transport::location" : [ 0.0 ],
					"upshot_transport::pulse[1]" : [ 0.0 ],
					"upshot_transport::taptotempo" : [ 0.0 ],
					"upshot_transport::timesig-beats" : [ 4 ],
					"upshot_transport::timesig-unit" : [ "4" ],
					"upshot_transport::transport[1]" : [ 1.0 ],
					"upshot_transport::units" : [ 0.0 ],
					"upshot_transport::volume" : [ 0.0 ],
					"upshot_polysynth[1]::carrier-attack" : [  ],
					"upshot_polysynth[1]::carrier-brightness" : [  ],
					"upshot_polysynth[1]::carrier-decay" : [  ],
					"upshot_polysynth[1]::carrier-ratio" : [  ],
					"upshot_polysynth[1]::carrier-release" : [  ],
					"upshot_polysynth[1]::carrier-sustain" : [  ],
					"upshot_polysynth[1]::flush" : [  ],
					"upshot_polysynth[1]::midiout" : [  ],
					"upshot_polysynth[1]::modulator-attack" : [  ],
					"upshot_polysynth[1]::modulator-decay" : [  ],
					"upshot_polysynth[1]::modulator-release" : [  ],
					"upshot_polysynth[1]::modulator-sustain" : [  ],
					"upshot_polysynth[1]::refresh" : [  ],
					"upshot_polysynth[1]::volume" : [  ],
					"upshot_polysynth[1]::wave-type" : [  ],
					"upshot_easyarp::chords" : [  ],
					"upshot_easyarp::collatz_global_quantize" : [  ],
					"upshot_easyarp::direction" : [  ],
					"upshot_easyarp::freetempo" : [  ],
					"upshot_easyarp::midiout" : [  ],
					"upshot_easyarp::octaves" : [  ],
					"upshot_easyarp::refresh" : [  ],
					"upshot_easyarp::transport[1]" : [  ],
					"upshot_beams[1]::beam" : [  ],
					"upshot_beams[1]::live.toggle" : [  ],
					"upshot_beams[1]::live.toggle[1]" : [  ],
					"upshot_beams[1]::live.toggle[2]" : [  ],
					"upshot_beams[1]::live.toggle[3]" : [  ],
					"upshot_beams[1]::live.toggle[4]" : [  ],
					"upshot_beams[1]::midiout" : [  ],
					"upshot_beams[1]::pitch_01" : [  ],
					"upshot_beams[1]::probability-one" : [  ],
					"upshot_beams[1]::probability-one[1]" : [  ],
					"upshot_beams[1]::probability-one[3]" : [  ],
					"upshot_beams[1]::probability-one[4]" : [  ],
					"upshot_beams[1]::probability-zero" : [  ],
					"upshot_beams[1]::probability-zero[1]" : [  ],
					"upshot_beams[1]::probability-zero[2]" : [  ],
					"upshot_beams[1]::random-range" : [  ],
					"upshot_beams[1]::random_note_01" : [  ],
					"upshot_beams[1]::refresh" : [  ],
					"upshot_beams[1]::root" : [  ],
					"upshot_beams[1]::scales" : [  ],
					"upshot_beams[1]::state" : [  ],
					"upshot_beams[1]::velocity_01" : [  ],
					"upshot_endlessreverb::fade" : [  ],
					"upshot_endlessreverb::grab" : [  ],
					"upshot_endlessreverb::volume" : [  ]
				}

			}
,
			"2" : 			{
				"id" : 2,
				"data" : 				{
					"upshot_polysynth::carrier-attack" : [ 0.0 ],
					"upshot_polysynth::carrier-brightness" : [ 0.0 ],
					"upshot_polysynth::carrier-decay" : [ 0.0 ],
					"upshot_polysynth::carrier-ratio" : [ 0.0 ],
					"upshot_polysynth::carrier-release" : [ 0.0 ],
					"upshot_polysynth::carrier-sustain" : [ 0.0 ],
					"upshot_polysynth::flush" : [ 0.0 ],
					"upshot_polysynth::midiout" : [ 1 ],
					"upshot_polysynth::modulator-attack" : [ 1.437485346916837 ],
					"upshot_polysynth::modulator-decay" : [ 81.965633541668893 ],
					"upshot_polysynth::modulator-release" : [ 81.965633541668623 ],
					"upshot_polysynth::modulator-sustain" : [ 17.32283464566936 ],
					"upshot_polysynth::refresh" : [ 0.0 ],
					"upshot_polysynth::volume" : [ -26.451076834441452 ],
					"upshot_polysynth::wave-type" : [ 1 ],
					"upshot_chords::chords" : [ 55.0 ],
					"upshot_chords::refresh[1]" : [ 0.0 ],
					"upshot_beams::beam" : [ 0.0 ],
					"upshot_beams::live.toggle" : [ 1.0 ],
					"upshot_beams::live.toggle[1]" : [ 0.0 ],
					"upshot_beams::live.toggle[2]" : [ 0.0 ],
					"upshot_beams::live.toggle[3]" : [ 0.0 ],
					"upshot_beams::live.toggle[4]" : [ 0.0 ],
					"upshot_beams::midiout" : [ 2 ],
					"upshot_beams::pitch_01" : [ 62.0 ],
					"upshot_beams::probability-one" : [ 30.0 ],
					"upshot_beams::probability-one[1]" : [ 100.0 ],
					"upshot_beams::probability-one[3]" : [ 0.0 ],
					"upshot_beams::probability-one[4]" : [ 30.0 ],
					"upshot_beams::probability-zero" : [ 100.0 ],
					"upshot_beams::probability-zero[1]" : [ 0.0 ],
					"upshot_beams::probability-zero[2]" : [ 0.0 ],
					"upshot_beams::random-range" : [ 0, 115 ],
					"upshot_beams::random_note_01" : [ 0.0 ],
					"upshot_beams::refresh" : [ 0.0 ],
					"upshot_beams::root" : [ 0.0 ],
					"upshot_beams::scales" : [ 1.0 ],
					"upshot_beams::state" : [ 1.0 ],
					"upshot_beams::velocity_01" : [ 79.999999999999957 ],
					"upshot_output::DSP state" : [ 1.0 ],
					"upshot_output::output volumes" : [ 0.0 ],
					"upshot_mixer::audio to 1" : [ 0.0 ],
					"upshot_mixer::audio to 2" : [ 1.0 ],
					"upshot_mixer::audio to 3" : [ 2.0 ],
					"upshot_mixer::audio to 4" : [ 3.0 ],
					"upshot_mixer::audio to 5" : [ 4.0 ],
					"upshot_mixer::audio to 6" : [ 5.0 ],
					"upshot_mixer::audio to 7" : [ 6.0 ],
					"upshot_mixer::audio to 8" : [ 7.0 ],
					"upshot_mixer::channel 1" : [ 0.0 ],
					"upshot_mixer::channel 2" : [ 0.0 ],
					"upshot_mixer::channel 3" : [ 0.0 ],
					"upshot_mixer::channel 4" : [ 0.0 ],
					"upshot_mixer::channel 5" : [ 0.0 ],
					"upshot_mixer::channel 6" : [ 0.0 ],
					"upshot_mixer::channel 7" : [ 0.0 ],
					"upshot_mixer::channel 8" : [ 0.0 ],
					"upshot_mixer::channel_01_mute" : [ 1.0 ],
					"upshot_mixer::channel_01_solo" : [ 0.0 ],
					"upshot_mixer::channel_01_solo[1]" : [ 0.0 ],
					"upshot_mixer::channel_02_mute" : [ 1.0 ],
					"upshot_mixer::channel_02_solo" : [ 0.0 ],
					"upshot_mixer::channel_02_solo[1]" : [ 0.0 ],
					"upshot_mixer::channel_02_solo[2]" : [ 0.0 ],
					"upshot_mixer::channel_03_mute" : [ 1.0 ],
					"upshot_mixer::channel_03_solo" : [ 0.0 ],
					"upshot_mixer::channel_03_solo[1]" : [ 0.0 ],
					"upshot_mixer::channel_03_solo[2]" : [ 0.0 ],
					"upshot_mixer::channel_04_mute" : [ 1.0 ],
					"upshot_mixer::channel_05_mute" : [ 1.0 ],
					"upshot_mixer::channel_06_mute" : [ 1.0 ],
					"upshot_mixer::channel_07_mute" : [ 1.0 ],
					"upshot_mixer::channel_08_mute" : [ 1.0 ],
					"upshot_transport::bars" : [ 92 ],
					"upshot_transport::beats" : [ 4 ],
					"upshot_transport::bpm" : [ 120.0 ],
					"upshot_transport::click-state" : [ 0.0 ],
					"upshot_transport::live.text" : [ 0.0 ],
					"upshot_transport::location" : [ 0.0 ],
					"upshot_transport::pulse[1]" : [ 0.0 ],
					"upshot_transport::taptotempo" : [ 0.0 ],
					"upshot_transport::timesig-beats" : [ 4 ],
					"upshot_transport::timesig-unit" : [ "4" ],
					"upshot_transport::transport[1]" : [ 1.0 ],
					"upshot_transport::units" : [ 420.0 ],
					"upshot_transport::volume" : [ 0.0 ],
					"upshot_polysynth[1]::carrier-attack" : [  ],
					"upshot_polysynth[1]::carrier-brightness" : [  ],
					"upshot_polysynth[1]::carrier-decay" : [  ],
					"upshot_polysynth[1]::carrier-ratio" : [  ],
					"upshot_polysynth[1]::carrier-release" : [  ],
					"upshot_polysynth[1]::carrier-sustain" : [  ],
					"upshot_polysynth[1]::flush" : [  ],
					"upshot_polysynth[1]::midiout" : [  ],
					"upshot_polysynth[1]::modulator-attack" : [  ],
					"upshot_polysynth[1]::modulator-decay" : [  ],
					"upshot_polysynth[1]::modulator-release" : [  ],
					"upshot_polysynth[1]::modulator-sustain" : [  ],
					"upshot_polysynth[1]::refresh" : [  ],
					"upshot_polysynth[1]::volume" : [  ],
					"upshot_polysynth[1]::wave-type" : [  ],
					"upshot_easyarp::chords" : [  ],
					"upshot_easyarp::collatz_global_quantize" : [  ],
					"upshot_easyarp::direction" : [  ],
					"upshot_easyarp::freetempo" : [  ],
					"upshot_easyarp::midiout" : [  ],
					"upshot_easyarp::octaves" : [  ],
					"upshot_easyarp::refresh" : [  ],
					"upshot_easyarp::transport[1]" : [  ],
					"upshot_beams[1]::beam" : [  ],
					"upshot_beams[1]::live.toggle" : [  ],
					"upshot_beams[1]::live.toggle[1]" : [  ],
					"upshot_beams[1]::live.toggle[2]" : [  ],
					"upshot_beams[1]::live.toggle[3]" : [  ],
					"upshot_beams[1]::live.toggle[4]" : [  ],
					"upshot_beams[1]::midiout" : [  ],
					"upshot_beams[1]::pitch_01" : [  ],
					"upshot_beams[1]::probability-one" : [  ],
					"upshot_beams[1]::probability-one[1]" : [  ],
					"upshot_beams[1]::probability-one[3]" : [  ],
					"upshot_beams[1]::probability-one[4]" : [  ],
					"upshot_beams[1]::probability-zero" : [  ],
					"upshot_beams[1]::probability-zero[1]" : [  ],
					"upshot_beams[1]::probability-zero[2]" : [  ],
					"upshot_beams[1]::random-range" : [  ],
					"upshot_beams[1]::random_note_01" : [  ],
					"upshot_beams[1]::refresh" : [  ],
					"upshot_beams[1]::root" : [  ],
					"upshot_beams[1]::scales" : [  ],
					"upshot_beams[1]::state" : [  ],
					"upshot_beams[1]::velocity_01" : [  ],
					"upshot_endlessreverb::fade" : [  ],
					"upshot_endlessreverb::grab" : [  ],
					"upshot_endlessreverb::volume" : [  ]
				}

			}

		}

	}

}
